cyminhook/__init__.py
cyminhook/_cyminhook.cp312-win32.pyd
cyminhook-0.1.5.data/data/include/MinHook.h
cyminhook-0.1.5.data/data/lib/minhook.x32.lib
cyminhook-0.1.5.data/data/lib/minhook/minhook-config-version.cmake
cyminhook-0.1.5.data/data/lib/minhook/minhook-config.cmake
cyminhook-0.1.5.data/data/lib/minhook/minhook-targets-release.cmake
cyminhook-0.1.5.data/data/lib/minhook/minhook-targets.cmake
cyminhook-0.1.5.dist-info/LICENSE
cyminhook-0.1.5.dist-info/METADATA
cyminhook-0.1.5.dist-info/NOTICE
cyminhook-0.1.5.dist-info/WHEEL
cyminhook-0.1.5.dist-info/top_level.txt
cyminhook-0.1.5.dist-info/RECORD
