Metadata-Version: 2.1
Name: cyminhook
Version: 0.1.5
Summary: Hook functions on Windows using MinHook
Home-page: https://github.com/segevfiner/cyminhook
Author: Segev Finer
Author-email: segev208@gmail.com
License: MIT
Project-URL: Documentation, https://segevfiner.github.io/cyminhook/
Project-URL: Issue Tracker, https://github.com/segevfiner/cyminhook/issues
Keywords: MinHook
Classifier: Development Status :: 3 - Alpha
Classifier: Environment :: Win32 (MS Windows)
Classifier: Intended Audience :: Developers
Classifier: Topic :: Security
Classifier: License :: OSI Approved :: MIT License
Classifier: Operating System :: Microsoft :: Windows
Classifier: Programming Language :: Cython
Classifier: Programming Language :: Python :: 3
Classifier: Programming Language :: Python :: 3.6
Classifier: Programming Language :: Python :: 3.7
Classifier: Programming Language :: Python :: 3.8
Classifier: Programming Language :: Python :: 3.9
Classifier: Programming Language :: Python :: 3.10
Classifier: Programming Language :: Python :: 3.11
Classifier: Programming Language :: Python :: 3.12
Classifier: Programming Language :: Python :: 3.13
Requires-Python: >=3.6
License-File: LICENSE
License-File: NOTICE
Provides-Extra: dev
Requires-Dist: sphinx==5.*; extra == "dev"
